gabrielgraph/__init__.py
gabrielgraph/_gabrielgraph.py
gabrielgraph/_tests/__init__.py
gabrielgraph/_tests/test_module.py
gabrielgraph-0.0.6.dist-info/licenses/LICENSE
gabrielgraph-0.0.6.dist-info/METADATA
gabrielgraph-0.0.6.dist-info/WHEEL
gabrielgraph-0.0.6.dist-info/top_level.txt
gabrielgraph-0.0.6.dist-info/RECORD
