Metadata-Version: 2.4
Name: GabrielGraph
Version: 0.0.6
Summary: A small class to create Gabriel Graphs
Home-page: https://github.com/GuignardLab/GabrielGraph
Author: Leo Guignard
Author-email: leo.guignard@univ-amu.fr
License: MIT
Project-URL: Bug Tracker, https://github.com/GuignardLab/GabrielGraph/issues
Project-URL: Documentation, https://github.com/GuignardLab/GabrielGraph#README.md
Project-URL: Source Code, https://github.com/GuignardLab/GabrielGraph
Project-URL: User Support, https://github.com/GuignardLab/GabrielGraph/issues
Classifier: Development Status :: 2 - Pre-Alpha
Classifier: Intended Audience :: Developers
Classifier: License :: OSI Approved :: MIT License
Classifier: Operating System :: OS Independent
Classifier: Programming Language :: Python
Classifier: Programming Language :: Python :: 3
Classifier: Programming Language :: Python :: 3 :: Only
Classifier: Programming Language :: Python :: 3.8
Classifier: Programming Language :: Python :: 3.9
Classifier: Programming Language :: Python :: 3.10
Classifier: Topic :: Scientific/Engineering :: Image Processing
Requires-Python: >=3.8
License-File: LICENSE
Requires-Dist: numpy
Requires-Dist: scipy
Provides-Extra: testing
Requires-Dist: tox; extra == "testing"
Requires-Dist: pytest; extra == "testing"
Requires-Dist: pytest-cov; extra == "testing"
Dynamic: license-file
